lzhasynctcpclient/__init__.py
lzhasynctcpclient/client.py
lzhasynctcpclient-0.1.6.dist-info/METADATA
lzhasynctcpclient-0.1.6.dist-info/WHEEL
lzhasynctcpclient-0.1.6.dist-info/top_level.txt
lzhasynctcpclient-0.1.6.dist-info/RECORD
